richcontext/scholapi/__init__.py
richcontext/scholapi/scholapi.py
richcontext_scholapi-1.2.0.dist-info/LICENSE
richcontext_scholapi-1.2.0.dist-info/METADATA
richcontext_scholapi-1.2.0.dist-info/WHEEL
richcontext_scholapi-1.2.0.dist-info/top_level.txt
richcontext_scholapi-1.2.0.dist-info/RECORD
