Metadata-Version: 2.1
Name: richcontext-scholapi
Version: 1.2.0
Summary: Rich Context API integrations for federating discovery services and metadata exchange across multiple scholarly infrastructure providers
Home-page: https://github.com/Coleridge-Initiative/RCApi
Author: Coleridge Initiative
Author-email: dataanalytics@coleridgeinitiative.org
License: MIT
Keywords: Rich Context,DOI,ISSN,ROR,ORCID,PubMed,EuropePMC,Crossref,DataCite,OpenAIRE,Unpaywall,dissemin,Semantic Scholar,RePEc,Dimensions,CORE,discovery,discovery service,federated API,federated metadata,knowledge graph,metadata API,metadata exchange,metadata,persistent identifiers,research publication ontology,research publications,scholarly infrastructure,scholarly metadata,scholarly publishing
Platform: UNKNOWN
Classifier: Programming Language :: Python :: 3
Classifier: License :: OSI Approved :: MIT License
Classifier: Operating System :: OS Independent
Classifier: Development Status :: 5 - Production/Stable
Classifier: Intended Audience :: Developers
Classifier: Intended Audience :: Education
Classifier: Intended Audience :: Information Technology
Classifier: Intended Audience :: Science/Research
Classifier: Topic :: Scientific/Engineering :: Artificial Intelligence
Classifier: Topic :: Scientific/Engineering :: Human Machine Interfaces
Classifier: Topic :: Scientific/Engineering :: Information Analysis
Requires-Python: >=3.5
Requires-Dist: beautifulsoup4
Requires-Dist: biopython
Requires-Dist: crossref-commons
Requires-Dist: dimcli
Requires-Dist: requests
Requires-Dist: requests-cache
Requires-Dist: selenium
Requires-Dist: xmltodict
